ailog/__init__.py
ailog/classes.py
ailog/resources/logging.conf
AILog-1.0.4.dist-info/METADATA
AILog-1.0.4.dist-info/WHEEL
AILog-1.0.4.dist-info/top_level.txt
AILog-1.0.4.dist-info/RECORD
